{
    "data": [
        {
            "h3": "870080002ffffff",
            "emission_per_cell": 280.5998462512822,
            "date": "25-11-2023 08:00"
        },
        {
            "h3": "870080003ffffff",
            "emission_per_cell": 140.4833610012414,
            "date": "25-11-2023 08:00"
        },
        {
            "h3": "870080006ffffff",
            "emission_per_cell": 280.5998462512822,
            "date": "25-11-2023 08:00"
        },
        {
            "h3": "870080010ffffff",
            "emission_per_cell": 141.253306379331,
            "date": "25-11-2023 08:00"
        },
        {
            "h3": "870080012ffffff",
            "emission_per_cell": 140.83439372165512,
            "date": "25-11-2023 08:00"
        },
        {
            "h3": "870080013ffffff",
            "emission_per_cell": 141.253306379331,
            "date": "25-11-2023 08:00"
        },
        {
            "h3": "870080014ffffff",
            "emission_per_cell": 141.253306379331,
            "date": "25-11-2023 08:00"
        },
        {
            "h3": "870080016ffffff",
            "emission_per_cell": 140.83439372165512,
            "date": "25-11-2023 08:00"
        },
        {
            "h3": "870080019ffffff",
            "emission_per_cell": 280.5998462512822,
            "date": "25-11-2023 08:00"
        },
        {
            "h3": "87008001affffff",
            "emission_per_cell": 141.253306379331,
            "date": "25-11-2023 08:00"
        },
        {
            "h3": "87008001cffffff",
            "emission_per_cell": 140.1164852500408,
            "date": "25-11-2023 08:00"
        },
        {
            "h3": "87008001dffffff",
            "emission_per_cell": 280.5998462512822,
            "date": "25-11-2023 08:00"
        },
        {
            "h3": "870080030ffffff",
            "emission_per_cell": 140.1164852500408,
            "date": "25-11-2023 08:00"
        },
        {
            "h3": "870080031ffffff",
            "emission_per_cell": 140.4833610012414,
            "date": "25-11-2023 08:00"
        },
        {
            "h3": "870080033ffffff",
            "emission_per_cell": 140.1164852500408,
            "date": "25-11-2023 08:00"
        },
        {
            "h3": "870080034ffffff",
            "emission_per_cell": 280.5998462512822,
            "date": "25-11-2023 08:00"
        },
        {
            "h3": "870080035ffffff",
            "emission_per_cell": 140.4833610012414,
            "date": "25-11-2023 08:00"
        },
        {
            "h3": "870080042ffffff",
            "emission_per_cell": 295.9043570416213,
            "date": "25-11-2023 08:00"
        },
        {
            "h3": "870080044ffffff",
            "emission_per_cell": 295.9043570416213,
            "date": "25-11-2023 08:00"
        },
        {
            "h3": "870080046ffffff",
            "emission_per_cell": 295.9043570416213,
            "date": "25-11-2023 08:00"
        },
        {
            "h3": "870080048ffffff",
            "emission_per_cell": 147.81857026939159,
            "date": "25-11-2023 08:00"
        },
        {
            "h3": "87008004affffff",
            "emission_per_cell": 147.81857026939159,
            "date": "25-11-2023 08:00"
        }
    ]
}